odoo/addons/ssi_fixed_asset_demo/README.rst
odoo/addons/ssi_fixed_asset_demo/__init__.py
odoo/addons/ssi_fixed_asset_demo/__manifest__.py
odoo/addons/ssi_fixed_asset_demo/demo/account_account_demo.xml
odoo/addons/ssi_fixed_asset_demo/demo/account_journal_demo.xml
odoo/addons/ssi_fixed_asset_demo/demo/fixed_asset_category_demo.xml
odoo/addons/ssi_fixed_asset_demo/static/description/banner.png
odoo/addons/ssi_fixed_asset_demo/static/description/icon.png
odoo14_addon_ssi_fixed_asset_demo-14.0.1.1.0.dist-info/METADATA
odoo14_addon_ssi_fixed_asset_demo-14.0.1.1.0.dist-info/WHEEL
odoo14_addon_ssi_fixed_asset_demo-14.0.1.1.0.dist-info/top_level.txt
odoo14_addon_ssi_fixed_asset_demo-14.0.1.1.0.dist-info/RECORD
